solotools/__init__.py
solotools/core/__init__.py
solotools/core/datetools.py
solotools/core/dbtools.py
solotools/core/exceltools.py
solotools/core/filetools.py
solotools/crypto/__init__.py
solotools/crypto/md5tool.py
solotools/extra/__init__.py
solotools-0.1.1.dist-info/LICENSE
solotools-0.1.1.dist-info/METADATA
solotools-0.1.1.dist-info/WHEEL
solotools-0.1.1.dist-info/top_level.txt
solotools-0.1.1.dist-info/RECORD
