Metadata-Version: 2.1
Name: solotools
Version: 0.1.1
Summary: SoloTools - 一个简单的工具集合
License-File: LICENSE
Requires-Dist: clickhouse-driver (>=0.2.6)
Requires-Dist: openpyxl (>=3.1.2)
Requires-Dist: PyMySQL (>=1.0.3)
